<?xml version="1.0" ?>
<annotation>
<folder>widerface</folder>
<filename>0--Parade_0_Parade_Parade_0_773.jpg</filename>
<source>
<database>wider face Database</database>
<annotation>PASCAL VOC2007</annotation>
<image>flickr</image>
<flickrid>-1</flickrid>
</source>
<owner>
<flickrid>yanyu</flickrid>
<name>yanyu</name>
</owner>
<size>
<width>1024</width>
<height>1702</height>
<depth>3</depth>
</size>
<segmented>0</segmented>
<object>
<name>face</name>
<pose>Unspecified</pose>
<truncated>1</truncated>
<difficult>0</difficult>
<bndbox>
<xmin>209</xmin>
<ymin>888</ymin>
<xmax>734</xmax>
<ymax>1663</ymax>
</bndbox>
<lm>
<x1>358.911</x1>
<y1>1134.723</y1>
<x2>640.384</x2>
<y2>1143.384</y2>
<x3>501.812</x3>
<y3>1277.625</y3>
<x4>371.902</x4>
<y4>1420.527</y4>
<x5>592.75</x5>
<y5>1420.527</y5>
<visible>0</visible>
<blur>0.9</blur>
</lm>
<has_lm>1</has_lm>
</object>
</annotation>
