<?xml version="1.0" ?>
<annotation>
<folder>widerface</folder>
<filename>0--Parade_0_Parade_marchingband_1_799.jpg</filename>
<source>
<database>wider face Database</database>
<annotation>PASCAL VOC2007</annotation>
<image>flickr</image>
<flickrid>-1</flickrid>
</source>
<owner>
<flickrid>yanyu</flickrid>
<name>yanyu</name>
</owner>
<size>
<width>1024</width>
<height>768</height>
<depth>3</depth>
</size>
<segmented>0</segmented>
<object>
<name>face</name>
<pose>Unspecified</pose>
<truncated>1</truncated>
<difficult>0</difficult>
<bndbox>
<xmin>78</xmin>
<ymin>238</ymin>
<xmax>92</xmax>
<ymax>255</ymax>
</bndbox>
<lm>
<x1>84.188</x1>
<y1>244.607</y1>
<x2>89.527</x2>
<y2>244.491</y2>
<x3>86.973</x3>
<y3>247.857</y3>
<x4>85.116</x4>
<y4>250.643</y4>
<x5>88.482</x5>
<y5>250.643</y5>
<visible>1</visible>
<blur>0.36</blur>
</lm>
<has_lm>1</has_lm>
</object>
<object>
<name>face</name>
<pose>Unspecified</pose>
<truncated>1</truncated>
<difficult>0</difficult>
<bndbox>
<xmin>113</xmin>
<ymin>212</ymin>
<xmax>124</xmax>
<ymax>227</ymax>
</bndbox>
<lm>
<x1>117.0</x1>
<y1>220.0</y1>
<x2>122.0</x2>
<y2>220.0</y2>
<x3>119.0</x3>
<y3>222.0</y3>
<x4>118.0</x4>
<y4>225.0</y4>
<x5>122.0</x5>
<y5>225.0</y5>
<visible>0</visible>
<blur>0.3</blur>
</lm>
<has_lm>1</has_lm>
</object>
<object>
<name>face</name>
<pose>Unspecified</pose>
<truncated>1</truncated>
<difficult>0</difficult>
<bndbox>
<xmin>134</xmin>
<ymin>260</ymin>
<xmax>149</xmax>
<ymax>275</ymax>
</bndbox>
<lm>
<x1>142.0</x1>
<y1>265.0</y1>
<x2>146.0</x2>
<y2>265.0</y2>
<x3>145.0</x3>
<y3>267.0</y3>
<x4>142.0</x4>
<y4>272.0</y4>
<x5>146.0</x5>
<y5>271.0</y5>
<visible>0</visible>
<blur>0.24</blur>
</lm>
<has_lm>1</has_lm>
</object>
<object>
<name>face</name>
<pose>Unspecified</pose>
<truncated>1</truncated>
<difficult>0</difficult>
<bndbox>
<xmin>163</xmin>
<ymin>250</ymin>
<xmax>177</xmax>
<ymax>267</ymax>
</bndbox>
<lm>
<x1>169.357</x1>
<y1>256.5</y1>
<x2>175.25</x2>
<y2>257.143</y2>
<x3>172.357</x3>
<y3>260.786</y3>
<x4>170.214</x4>
<y4>262.929</y4>
<x5>174.071</x5>
<y5>262.821</y5>
<visible>1</visible>
<blur>0.41</blur>
</lm>
<has_lm>1</has_lm>
</object>
<object>
<name>face</name>
<pose>Unspecified</pose>
<truncated>1</truncated>
<difficult>0</difficult>
<bndbox>
<xmin>201</xmin>
<ymin>218</ymin>
<xmax>211</xmax>
<ymax>230</ymax>
</bndbox>
<lm>
<x1>203.0</x1>
<y1>222.0</y1>
<x2>207.0</x2>
<y2>223.0</y2>
<x3>204.0</x3>
<y3>225.0</y3>
<x4>203.0</x4>
<y4>227.0</y4>
<x5>206.0</x5>
<y5>227.0</y5>
<visible>0</visible>
<blur>0.22</blur>
</lm>
<has_lm>1</has_lm>
</object>
<object>
<name>face</name>
<pose>Unspecified</pose>
<truncated>1</truncated>
<difficult>0</difficult>
<bndbox>
<xmin>182</xmin>
<ymin>266</ymin>
<xmax>197</xmax>
<ymax>283</ymax>
</bndbox>
<lm>
<x1>189.723</x1>
<y1>271.487</y1>
<x2>195.527</x2>
<y2>271.152</y2>
<x3>193.741</x3>
<y3>274.835</y3>
<x4>191.062</x4>
<y4>278.406</y4>
<x5>194.969</x5>
<y5>278.295</y5>
<visible>0</visible>
<blur>0.32</blur>
</lm>
<has_lm>1</has_lm>
</object>
<object>
<name>face</name>
<pose>Unspecified</pose>
<truncated>1</truncated>
<difficult>0</difficult>
<bndbox>
<xmin>245</xmin>
<ymin>279</ymin>
<xmax>263</xmax>
<ymax>294</ymax>
</bndbox>
<lm>
<x1>254.116</x1>
<y1>281.973</y1>
<x2>259.571</x2>
<y2>281.277</y2>
<x3>257.83</x3>
<y3>284.411</y3>
<x4>255.161</x4>
<y4>287.661</y4>
<x5>259.223</x5>
<y5>287.08</y5>
<visible>1</visible>
<blur>0.26</blur>
</lm>
<has_lm>1</has_lm>
</object>
<object>
<name>face</name>
<pose>Unspecified</pose>
<truncated>1</truncated>
<difficult>0</difficult>
<bndbox>
<xmin>304</xmin>
<ymin>265</ymin>
<xmax>320</xmax>
<ymax>282</ymax>
</bndbox>
<lm>
<x1>309.0</x1>
<y1>272.0</y1>
<x2>314.0</x2>
<y2>270.0</y2>
<x3>314.0</x3>
<y3>275.0</y3>
<x4>312.0</x4>
<y4>279.0</y4>
<x5>316.0</x5>
<y5>278.0</y5>
<visible>1</visible>
<blur>0.29</blur>
</lm>
<has_lm>1</has_lm>
</object>
<object>
<name>face</name>
<pose>Unspecified</pose>
<truncated>1</truncated>
<difficult>0</difficult>
<bndbox>
<xmin>328</xmin>
<ymin>295</ymin>
<xmax>344</xmax>
<ymax>315</ymax>
</bndbox>
<lm>
<x1>337.0</x1>
<y1>303.0</y1>
<x2>343.0</x2>
<y2>302.0</y2>
<x3>341.0</x3>
<y3>307.0</y3>
<x4>339.0</x4>
<y4>312.0</y4>
<x5>343.0</x5>
<y5>312.0</y5>
<visible>0</visible>
<blur>0.32</blur>
</lm>
<has_lm>1</has_lm>
</object>
<object>
<name>face</name>
<pose>Unspecified</pose>
<truncated>1</truncated>
<difficult>0</difficult>
<bndbox>
<xmin>389</xmin>
<ymin>281</ymin>
<xmax>406</xmax>
<ymax>300</ymax>
</bndbox>
<lm>
<x1>396.0</x1>
<y1>290.0</y1>
<x2>401.0</x2>
<y2>289.0</y2>
<x3>400.0</x3>
<y3>294.0</y3>
<x4>399.0</x4>
<y4>297.0</y4>
<x5>403.0</x5>
<y5>296.0</y5>
<visible>1</visible>
<blur>0.27</blur>
</lm>
<has_lm>1</has_lm>
</object>
<object>
<name>face</name>
<pose>Unspecified</pose>
<truncated>1</truncated>
<difficult>0</difficult>
<bndbox>
<xmin>406</xmin>
<ymin>293</ymin>
<xmax>427</xmax>
<ymax>314</ymax>
</bndbox>
<lm>
<x1>415.808</x1>
<y1>298.987</y1>
<x2>424.527</x2>
<y2>299.263</y2>
<x3>421.897</x3>
<y3>302.446</y3>
<x4>418.438</x4>
<y4>307.567</y4>
<x5>422.589</x5>
<y5>307.567</y5>
<visible>1</visible>
<blur>0.37</blur>
</lm>
<has_lm>1</has_lm>
</object>
<object>
<name>face</name>
<pose>Unspecified</pose>
<truncated>1</truncated>
<difficult>0</difficult>
<bndbox>
<xmin>436</xmin>
<ymin>290</ymin>
<xmax>458</xmax>
<ymax>307</ymax>
</bndbox>
<lm>
<x1>442.857</x1>
<y1>292.929</y1>
<x2>453.857</x2>
<y2>292.786</y2>
<x3>450.429</x3>
<y3>296.357</y3>
<x4>447.571</x4>
<y4>301.357</y4>
<x5>452.714</x5>
<y5>301.071</y5>
<visible>1</visible>
<blur>0.45</blur>
</lm>
<has_lm>1</has_lm>
</object>
<object>
<name>face</name>
<pose>Unspecified</pose>
<truncated>1</truncated>
<difficult>0</difficult>
<bndbox>
<xmin>522</xmin>
<ymin>328</ymin>
<xmax>543</xmax>
<ymax>346</ymax>
</bndbox>
<lm>
<x1>530.0</x1>
<y1>332.0</y1>
<x2>539.0</x2>
<y2>330.0</y2>
<x3>536.0</x3>
<y3>335.0</y3>
<x4>533.0</x4>
<y4>341.0</y4>
<x5>539.0</x5>
<y5>340.0</y5>
<visible>0</visible>
<blur>0.29</blur>
</lm>
<has_lm>1</has_lm>
</object>
<object>
<name>face</name>
<pose>Unspecified</pose>
<truncated>1</truncated>
<difficult>0</difficult>
<bndbox>
<xmin>643</xmin>
<ymin>320</ymin>
<xmax>666</xmax>
<ymax>342</ymax>
</bndbox>
<lm>
<x1>653.241</x1>
<y1>323.062</y1>
<x2>661.893</x2>
<y2>323.67</y2>
<x3>661.438</x3>
<y3>328.83</y3>
<x4>653.393</x4>
<y4>334.446</y4>
<x5>661.134</x5>
<y5>334.75</y5>
<visible>0</visible>
<blur>0.28</blur>
</lm>
<has_lm>1</has_lm>
</object>
<object>
<name>face</name>
<pose>Unspecified</pose>
<truncated>1</truncated>
<difficult>0</difficult>
<bndbox>
<xmin>653</xmin>
<ymin>224</ymin>
<xmax>670</xmax>
<ymax>249</ymax>
</bndbox>
<lm>
<x1>664.143</x1>
<y1>233.031</y1>
<x2>668.933</x2>
<y2>232.866</y2>
<x3>669.429</x3>
<y3>236.996</y3>
<x4>664.804</x4>
<y4>239.308</y4>
<x5>669.924</x5>
<y5>239.473</y5>
<visible>1</visible>
<blur>0.36</blur>
</lm>
<has_lm>1</has_lm>
</object>
<object>
<name>face</name>
<pose>Unspecified</pose>
<truncated>1</truncated>
<difficult>0</difficult>
<bndbox>
<xmin>793</xmin>
<ymin>337</ymin>
<xmax>816</xmax>
<ymax>367</ymax>
</bndbox>
<lm>
<x1>804.46</x1>
<y1>348.429</y1>
<x2>812.714</x2>
<y2>348.237</y2>
<x3>811.754</x3>
<y3>355.339</y3>
<x4>804.076</x4>
<y4>359.562</y4>
<x5>810.987</x5>
<y5>359.562</y5>
<visible>0</visible>
<blur>0.47</blur>
</lm>
<has_lm>1</has_lm>
</object>
<object>
<name>face</name>
<pose>Unspecified</pose>
<truncated>1</truncated>
<difficult>0</difficult>
<bndbox>
<xmin>535</xmin>
<ymin>311</ymin>
<xmax>551</xmax>
<ymax>328</ymax>
</bndbox>
<lm>
<x1>540.0</x1>
<y1>316.0</y1>
<x2>547.0</x2>
<y2>315.0</y2>
<x3>544.0</x3>
<y3>320.0</y3>
<x4>542.0</x4>
<y4>324.0</y4>
<x5>547.0</x5>
<y5>323.0</y5>
<visible>0</visible>
<blur>0.26</blur>
</lm>
<has_lm>1</has_lm>
</object>
<object>
<name>face</name>
<pose>Unspecified</pose>
<truncated>1</truncated>
<difficult>0</difficult>
<bndbox>
<xmin>29</xmin>
<ymin>220</ymin>
<xmax>40</xmax>
<ymax>235</ymax>
</bndbox>
<lm>
<x1>33.42</x1>
<y1>226.804</y1>
<x2>38.134</x2>
<y2>226.804</y2>
<x3>36.17</x3>
<y3>229.554</y3>
<x4>33.812</x4>
<y4>231.616</y4>
<x5>38.036</x5>
<y5>231.42</y5>
<visible>1</visible>
<blur>0.34</blur>
</lm>
<has_lm>1</has_lm>
</object>
<object>
<name>face</name>
<pose>Unspecified</pose>
<truncated>1</truncated>
<difficult>0</difficult>
<bndbox>
<xmin>3</xmin>
<ymin>232</ymin>
<xmax>14</xmax>
<ymax>247</ymax>
</bndbox>
<lm>
<x1>8.0</x1>
<y1>240.0</y1>
<x2>14.0</x2>
<y2>239.0</y2>
<x3>12.0</x3>
<y3>243.0</y3>
<x4>9.0</x4>
<y4>245.0</y4>
<x5>14.0</x5>
<y5>245.0</y5>
<visible>1</visible>
<blur>0.29</blur>
</lm>
<has_lm>1</has_lm>
</object>
<object>
<name>face</name>
<pose>Unspecified</pose>
<truncated>1</truncated>
<difficult>0</difficult>
<bndbox>
<xmin>20</xmin>
<ymin>215</ymin>
<xmax>32</xmax>
<ymax>231</ymax>
</bndbox>
<lm>
<x1>24.0</x1>
<y1>221.0</y1>
<x2>30.0</x2>
<y2>221.0</y2>
<x3>26.0</x3>
<y3>224.0</y3>
<x4>24.0</x4>
<y4>228.0</y4>
<x5>28.0</x5>
<y5>229.0</y5>
<visible>1</visible>
<blur>0.26</blur>
</lm>
<has_lm>1</has_lm>
</object>
</annotation>
