<?xml version="1.0" ?>
<annotation>
<folder>widerface</folder>
<filename>1--Handshaking_1_Handshaking_Handshaking_1_288.jpg</filename>
<source>
<database>wider face Database</database>
<annotation>PASCAL VOC2007</annotation>
<image>flickr</image>
<flickrid>-1</flickrid>
</source>
<owner>
<flickrid>yanyu</flickrid>
<name>yanyu</name>
</owner>
<size>
<width>1024</width>
<height>767</height>
<depth>3</depth>
</size>
<segmented>0</segmented>
<object>
<name>face</name>
<pose>Unspecified</pose>
<truncated>1</truncated>
<difficult>0</difficult>
<bndbox>
<xmin>336</xmin>
<ymin>82</ymin>
<xmax>448</xmax>
<ymax>244</ymax>
</bndbox>
<lm>
<x1>366.165</x1>
<y1>148.312</y1>
<x2>419.875</x2>
<y2>150.339</y2>
<x3>393.527</x3>
<y3>178.714</y3>
<x4>374.272</x4>
<y4>209.116</y4>
<x5>411.768</x5>
<y5>208.103</y5>
<visible>0</visible>
<blur>0.77</blur>
</lm>
<has_lm>1</has_lm>
</object>
</annotation>
