<?xml version="1.0" ?>
<annotation>
<folder>widerface</folder>
<filename>13--Interview_13_Interview_Interview_Sequences_13_786.jpg</filename>
<source>
<database>wider face Database</database>
<annotation>PASCAL VOC2007</annotation>
<image>flickr</image>
<flickrid>-1</flickrid>
</source>
<owner>
<flickrid>yanyu</flickrid>
<name>yanyu</name>
</owner>
<size>
<width>1024</width>
<height>934</height>
<depth>3</depth>
</size>
<segmented>0</segmented>
<object>
<name>face</name>
<pose>Unspecified</pose>
<truncated>1</truncated>
<difficult>0</difficult>
<bndbox>
<xmin>266</xmin>
<ymin>152</ymin>
<xmax>710</xmax>
<ymax>774</ymax>
</bndbox>
<lm>
<x1>444.728</x1>
<y1>392.509</y1>
<x2>635.259</x2>
<y2>404.174</y2>
<x3>588.598</x3>
<y3>513.049</y3>
<x4>456.393</x4>
<y4>629.701</y4>
<x5>623.594</x5>
<y5>629.701</y5>
<visible>0</visible>
<blur>0.98</blur>
</lm>
<has_lm>1</has_lm>
</object>
</annotation>
