<?xml version="1.0" ?>
<annotation>
<folder>widerface</folder>
<filename>29--Students_Schoolkids_29_Students_Schoolkids_Students_Schoolkids_29_720.jpg</filename>
<source>
<database>wider face Database</database>
<annotation>PASCAL VOC2007</annotation>
<image>flickr</image>
<flickrid>-1</flickrid>
</source>
<owner>
<flickrid>yanyu</flickrid>
<name>yanyu</name>
</owner>
<size>
<width>1024</width>
<height>683</height>
<depth>3</depth>
</size>
<segmented>0</segmented>
<object>
<name>face</name>
<pose>Unspecified</pose>
<truncated>1</truncated>
<difficult>0</difficult>
<bndbox>
<xmin>420</xmin>
<ymin>126</ymin>
<xmax>528</xmax>
<ymax>272</ymax>
</bndbox>
<lm>
<x1>438.723</x1>
<y1>152.741</y1>
<x2>489.058</x2>
<y2>153.656</y2>
<x3>458.857</x3>
<y3>183.857</y3>
<x4>441.469</x4>
<y4>210.397</y4>
<x5>486.312</x5>
<y5>214.058</y5>
<visible>0</visible>
<blur>0.78</blur>
</lm>
<has_lm>1</has_lm>
</object>
</annotation>
