<?xml version="1.0" ?>
<annotation>
<folder>widerface</folder>
<filename>3--Riot_3_Riot_Riot_3_1023.jpg</filename>
<source>
<database>wider face Database</database>
<annotation>PASCAL VOC2007</annotation>
<image>flickr</image>
<flickrid>-1</flickrid>
</source>
<owner>
<flickrid>yanyu</flickrid>
<name>yanyu</name>
</owner>
<size>
<width>1024</width>
<height>891</height>
<depth>3</depth>
</size>
<segmented>0</segmented>
<object>
<name>face</name>
<pose>Unspecified</pose>
<truncated>1</truncated>
<difficult>0</difficult>
<bndbox>
<xmin>304</xmin>
<ymin>565</ymin>
<xmax>342</xmax>
<ymax>614</ymax>
</bndbox>
<lm>
<x1>320.281</x1>
<y1>582.844</y1>
<x2>336.763</x2>
<y2>583.795</y2>
<x3>335.179</x3>
<y3>592.036</y3>
<x4>327.254</x4>
<y4>603.763</y4>
<x5>338.348</x5>
<y5>605.348</y5>
<visible>0</visible>
<blur>0.56</blur>
</lm>
<has_lm>1</has_lm>
</object>
<object>
<name>face</name>
<pose>Unspecified</pose>
<truncated>1</truncated>
<difficult>0</difficult>
<bndbox>
<xmin>354</xmin>
<ymin>575</ymin>
<xmax>392</xmax>
<ymax>621</ymax>
</bndbox>
<lm>
<x1>368.714</x1>
<y1>591.857</y1>
<x2>388.429</x2>
<y2>591.571</y2>
<x3>380.429</x3>
<y3>603.0</y3>
<x4>371.857</x4>
<y4>611.286</y4>
<x5>383.0</x5>
<y5>612.143</y5>
<visible>0</visible>
<blur>0.55</blur>
</lm>
<has_lm>1</has_lm>
</object>
<object>
<name>face</name>
<pose>Unspecified</pose>
<truncated>1</truncated>
<difficult>0</difficult>
<bndbox>
<xmin>408</xmin>
<ymin>566</ymin>
<xmax>442</xmax>
<ymax>605</ymax>
</bndbox>
<lm>
<x1>415.5</x1>
<y1>577.5</y1>
<x2>431.75</x2>
<y2>574.5</y2>
<x3>424.75</x3>
<y3>589.0</y3>
<x4>422.25</x4>
<y4>597.5</y4>
<x5>431.25</x5>
<y5>596.25</y5>
<visible>0</visible>
<blur>0.49</blur>
</lm>
<has_lm>1</has_lm>
</object>
<object>
<name>face</name>
<pose>Unspecified</pose>
<truncated>1</truncated>
<difficult>0</difficult>
<bndbox>
<xmin>474</xmin>
<ymin>566</ymin>
<xmax>519</xmax>
<ymax>603</ymax>
</bndbox>
<lm>
<x1>484.603</x1>
<y1>587.562</y1>
<x2>501.433</x2>
<y2>579.147</y2>
<x3>495.339</x3>
<y3>595.688</y3>
<x4>500.562</x4>
<y4>598.589</y4>
<x5>509.268</x5>
<y5>594.237</y5>
<visible>1</visible>
<blur>0.5</blur>
</lm>
<has_lm>1</has_lm>
</object>
<object>
<name>face</name>
<pose>Unspecified</pose>
<truncated>1</truncated>
<difficult>0</difficult>
<bndbox>
<xmin>363</xmin>
<ymin>376</ymin>
<xmax>384</xmax>
<ymax>405</ymax>
</bndbox>
<has_lm>0</has_lm>
</object>
<object>
<name>face</name>
<pose>Unspecified</pose>
<truncated>1</truncated>
<difficult>0</difficult>
<bndbox>
<xmin>393</xmin>
<ymin>370</ymin>
<xmax>412</xmax>
<ymax>394</ymax>
</bndbox>
<has_lm>0</has_lm>
</object>
<object>
<name>face</name>
<pose>Unspecified</pose>
<truncated>1</truncated>
<difficult>0</difficult>
<bndbox>
<xmin>329</xmin>
<ymin>387</ymin>
<xmax>351</xmax>
<ymax>417</ymax>
</bndbox>
<has_lm>0</has_lm>
</object>
<object>
<name>face</name>
<pose>Unspecified</pose>
<truncated>1</truncated>
<difficult>0</difficult>
<bndbox>
<xmin>289</xmin>
<ymin>399</ymin>
<xmax>316</xmax>
<ymax>425</ymax>
</bndbox>
<has_lm>0</has_lm>
</object>
</annotation>
