<?xml version="1.0" ?>
<annotation>
<folder>widerface</folder>
<filename>35--Basketball_35_Basketball_playingbasketball_35_294.jpg</filename>
<source>
<database>wider face Database</database>
<annotation>PASCAL VOC2007</annotation>
<image>flickr</image>
<flickrid>-1</flickrid>
</source>
<owner>
<flickrid>yanyu</flickrid>
<name>yanyu</name>
</owner>
<size>
<width>1024</width>
<height>1583</height>
<depth>3</depth>
</size>
<segmented>0</segmented>
<object>
<name>face</name>
<pose>Unspecified</pose>
<truncated>1</truncated>
<difficult>0</difficult>
<bndbox>
<xmin>452</xmin>
<ymin>323</ymin>
<xmax>505</xmax>
<ymax>388</ymax>
</bndbox>
<lm>
<x1>478.5</x1>
<y1>336.219</y1>
<x2>493.938</x2>
<y2>336.219</y2>
<x3>502.062</x3>
<y3>345.969</y3>
<x4>490.688</x4>
<y4>360.188</y4>
<x5>503.281</x5>
<y5>367.906</y5>
<visible>1</visible>
<blur>0.54</blur>
</lm>
<has_lm>1</has_lm>
</object>
<object>
<name>face</name>
<pose>Unspecified</pose>
<truncated>1</truncated>
<difficult>0</difficult>
<bndbox>
<xmin>584</xmin>
<ymin>621</ymin>
<xmax>628</xmax>
<ymax>658</ymax>
</bndbox>
<lm>
<x1>594.759</x1>
<y1>631.58</y1>
<x2>616.348</x2>
<y2>631.027</y2>
<x3>605.0</x3>
<y3>629.366</y3>
<x4>598.357</x4>
<y4>646.25</y4>
<x5>612.75</x5>
<y5>647.634</y5>
<visible>0</visible>
<blur>0.49</blur>
</lm>
<has_lm>1</has_lm>
</object>
<object>
<name>face</name>
<pose>Unspecified</pose>
<truncated>1</truncated>
<difficult>0</difficult>
<bndbox>
<xmin>874</xmin>
<ymin>148</ymin>
<xmax>935</xmax>
<ymax>197</ymax>
</bndbox>
<lm>
<x1>897.0</x1>
<y1>172.0</y1>
<x2>893.0</x2>
<y2>171.0</y2>
<x3>869.0</x3>
<y3>195.0</y3>
<x4>877.0</x4>
<y4>200.0</y4>
<x5>882.0</x5>
<y5>200.0</y5>
<visible>1</visible>
<blur>0.42</blur>
</lm>
<has_lm>1</has_lm>
</object>
</annotation>
