<?xml version="1.0" ?>
<annotation>
<folder>widerface</folder>
<filename>40--Gymnastics_40_Gymnastics_Gymnastics_40_913.jpg</filename>
<source>
<database>wider face Database</database>
<annotation>PASCAL VOC2007</annotation>
<image>flickr</image>
<flickrid>-1</flickrid>
</source>
<owner>
<flickrid>yanyu</flickrid>
<name>yanyu</name>
</owner>
<size>
<width>1024</width>
<height>1334</height>
<depth>3</depth>
</size>
<segmented>0</segmented>
<object>
<name>face</name>
<pose>Unspecified</pose>
<truncated>1</truncated>
<difficult>0</difficult>
<bndbox>
<xmin>511</xmin>
<ymin>146</ymin>
<xmax>646</xmax>
<ymax>328</ymax>
</bndbox>
<lm>
<x1>545.875</x1>
<y1>219.29</y1>
<x2>608.978</x2>
<y2>219.29</y2>
<x3>580.295</x3>
<y3>262.888</y3>
<x4>542.433</x4>
<y4>275.509</y4>
<x5>610.125</x5>
<y5>272.067</y5>
<visible>0</visible>
<blur>0.92</blur>
</lm>
<has_lm>1</has_lm>
</object>
<object>
<name>face</name>
<pose>Unspecified</pose>
<truncated>1</truncated>
<difficult>0</difficult>
<bndbox>
<xmin>894</xmin>
<ymin>149</ymin>
<xmax>1022</xmax>
<ymax>331</ymax>
</bndbox>
<lm>
<x1>924.929</x1>
<y1>236.714</y1>
<x2>988.929</x2>
<y2>224.143</y2>
<x3>962.643</x3>
<y3>266.429</y3>
<x4>944.357</x4>
<y4>292.714</y4>
<x5>1000.357</x5>
<y5>277.857</y5>
<visible>0</visible>
<blur>0.84</blur>
</lm>
<has_lm>1</has_lm>
</object>
<object>
<name>face</name>
<pose>Unspecified</pose>
<truncated>1</truncated>
<difficult>0</difficult>
<bndbox>
<xmin>224</xmin>
<ymin>920</ymin>
<xmax>300</xmax>
<ymax>1006</ymax>
</bndbox>
<lm>
<x1>246.375</x1>
<y1>960.879</y1>
<x2>275.004</x2>
<y2>960.339</y2>
<x3>260.42</x3>
<y3>976.545</y3>
<x4>246.375</x4>
<y4>986.268</y4>
<x5>277.705</x5>
<y5>985.188</y5>
<visible>0</visible>
<blur>0.73</blur>
</lm>
<has_lm>1</has_lm>
</object>
<object>
<name>face</name>
<pose>Unspecified</pose>
<truncated>1</truncated>
<difficult>0</difficult>
<bndbox>
<xmin>453</xmin>
<ymin>1011</ymin>
<xmax>529</xmax>
<ymax>1092</ymax>
</bndbox>
<lm>
<x1>470.143</x1>
<y1>1048.964</y1>
<x2>496.098</x2>
<y2>1045.911</y2>
<x3>482.357</x3>
<y3>1062.705</y3>
<x4>474.723</x4>
<y4>1074.92</y4>
<x5>496.098</x5>
<y5>1072.375</y5>
<visible>0</visible>
<blur>0.71</blur>
</lm>
<has_lm>1</has_lm>
</object>
</annotation>
