<?xml version="1.0" ?>
<annotation>
<folder>widerface</folder>
<filename>44--Aerobics_44_Aerobics_Aerobics_44_329.jpg</filename>
<source>
<database>wider face Database</database>
<annotation>PASCAL VOC2007</annotation>
<image>flickr</image>
<flickrid>-1</flickrid>
</source>
<owner>
<flickrid>yanyu</flickrid>
<name>yanyu</name>
</owner>
<size>
<width>1024</width>
<height>596</height>
<depth>3</depth>
</size>
<segmented>0</segmented>
<object>
<name>face</name>
<pose>Unspecified</pose>
<truncated>1</truncated>
<difficult>0</difficult>
<bndbox>
<xmin>326</xmin>
<ymin>74</ymin>
<xmax>342</xmax>
<ymax>92</ymax>
</bndbox>
</object>
<object>
<name>face</name>
<pose>Unspecified</pose>
<truncated>1</truncated>
<difficult>0</difficult>
<bndbox>
<xmin>874</xmin>
<ymin>292</ymin>
<xmax>889</xmax>
<ymax>319</ymax>
</bndbox>
</object>
<object>
<name>face</name>
<pose>Unspecified</pose>
<truncated>1</truncated>
<difficult>0</difficult>
<bndbox>
<xmin>943</xmin>
<ymin>252</ymin>
<xmax>956</xmax>
<ymax>272</ymax>
</bndbox>
</object>
<object>
<name>face</name>
<pose>Unspecified</pose>
<truncated>1</truncated>
<difficult>0</difficult>
<bndbox>
<xmin>682</xmin>
<ymin>321</ymin>
<xmax>702</xmax>
<ymax>349</ymax>
</bndbox>
</object>
<object>
<name>face</name>
<pose>Unspecified</pose>
<truncated>1</truncated>
<difficult>0</difficult>
<bndbox>
<xmin>680</xmin>
<ymin>250</ymin>
<xmax>691</xmax>
<ymax>267</ymax>
</bndbox>
</object>
</annotation>
