<?xml version="1.0" ?>
<annotation>
<folder>widerface</folder>
<filename>47--Matador_Bullfighter_47_Matador_Bullfighter_matadorbullfighting_47_236.jpg</filename>
<source>
<database>wider face Database</database>
<annotation>PASCAL VOC2007</annotation>
<image>flickr</image>
<flickrid>-1</flickrid>
</source>
<owner>
<flickrid>yanyu</flickrid>
<name>yanyu</name>
</owner>
<size>
<width>1024</width>
<height>1366</height>
<depth>3</depth>
</size>
<segmented>0</segmented>
<object>
<name>face</name>
<pose>Unspecified</pose>
<truncated>1</truncated>
<difficult>0</difficult>
<bndbox>
<xmin>989</xmin>
<ymin>95</ymin>
<xmax>1011</xmax>
<ymax>121</ymax>
</bndbox>
</object>
<object>
<name>face</name>
<pose>Unspecified</pose>
<truncated>1</truncated>
<difficult>0</difficult>
<bndbox>
<xmin>943</xmin>
<ymin>47</ymin>
<xmax>962</xmax>
<ymax>69</ymax>
</bndbox>
</object>
<object>
<name>face</name>
<pose>Unspecified</pose>
<truncated>1</truncated>
<difficult>0</difficult>
<bndbox>
<xmin>973</xmin>
<ymin>28</ymin>
<xmax>986</xmax>
<ymax>43</ymax>
</bndbox>
</object>
<object>
<name>face</name>
<pose>Unspecified</pose>
<truncated>1</truncated>
<difficult>0</difficult>
<bndbox>
<xmin>1005</xmin>
<ymin>24</ymin>
<xmax>1016</xmax>
<ymax>38</ymax>
</bndbox>
</object>
<object>
<name>face</name>
<pose>Unspecified</pose>
<truncated>1</truncated>
<difficult>0</difficult>
<bndbox>
<xmin>828</xmin>
<ymin>129</ymin>
<xmax>852</xmax>
<ymax>154</ymax>
</bndbox>
</object>
<object>
<name>face</name>
<pose>Unspecified</pose>
<truncated>1</truncated>
<difficult>0</difficult>
<bndbox>
<xmin>855</xmin>
<ymin>156</ymin>
<xmax>870</xmax>
<ymax>175</ymax>
</bndbox>
</object>
<object>
<name>face</name>
<pose>Unspecified</pose>
<truncated>1</truncated>
<difficult>0</difficult>
<bndbox>
<xmin>794</xmin>
<ymin>114</ymin>
<xmax>813</xmax>
<ymax>141</ymax>
</bndbox>
</object>
<object>
<name>face</name>
<pose>Unspecified</pose>
<truncated>1</truncated>
<difficult>0</difficult>
<bndbox>
<xmin>726</xmin>
<ymin>183</ymin>
<xmax>744</xmax>
<ymax>205</ymax>
</bndbox>
</object>
<object>
<name>face</name>
<pose>Unspecified</pose>
<truncated>1</truncated>
<difficult>0</difficult>
<bndbox>
<xmin>716</xmin>
<ymin>108</ymin>
<xmax>737</xmax>
<ymax>135</ymax>
</bndbox>
</object>
<object>
<name>face</name>
<pose>Unspecified</pose>
<truncated>1</truncated>
<difficult>0</difficult>
<bndbox>
<xmin>750</xmin>
<ymin>48</ymin>
<xmax>764</xmax>
<ymax>66</ymax>
</bndbox>
</object>
<object>
<name>face</name>
<pose>Unspecified</pose>
<truncated>1</truncated>
<difficult>0</difficult>
<bndbox>
<xmin>680</xmin>
<ymin>45</ymin>
<xmax>694</xmax>
<ymax>63</ymax>
</bndbox>
</object>
<object>
<name>face</name>
<pose>Unspecified</pose>
<truncated>1</truncated>
<difficult>0</difficult>
<bndbox>
<xmin>673</xmin>
<ymin>187</ymin>
<xmax>699</xmax>
<ymax>225</ymax>
</bndbox>
</object>
<object>
<name>face</name>
<pose>Unspecified</pose>
<truncated>1</truncated>
<difficult>0</difficult>
<bndbox>
<xmin>697</xmin>
<ymin>180</ymin>
<xmax>713</xmax>
<ymax>196</ymax>
</bndbox>
</object>
<object>
<name>face</name>
<pose>Unspecified</pose>
<truncated>1</truncated>
<difficult>0</difficult>
<bndbox>
<xmin>758</xmin>
<ymin>172</ymin>
<xmax>776</xmax>
<ymax>196</ymax>
</bndbox>
</object>
<object>
<name>face</name>
<pose>Unspecified</pose>
<truncated>1</truncated>
<difficult>0</difficult>
<bndbox>
<xmin>601</xmin>
<ymin>192</ymin>
<xmax>624</xmax>
<ymax>214</ymax>
</bndbox>
</object>
<object>
<name>face</name>
<pose>Unspecified</pose>
<truncated>1</truncated>
<difficult>0</difficult>
<bndbox>
<xmin>588</xmin>
<ymin>132</ymin>
<xmax>607</xmax>
<ymax>155</ymax>
</bndbox>
</object>
<object>
<name>face</name>
<pose>Unspecified</pose>
<truncated>1</truncated>
<difficult>0</difficult>
<bndbox>
<xmin>523</xmin>
<ymin>107</ymin>
<xmax>546</xmax>
<ymax>134</ymax>
</bndbox>
</object>
<object>
<name>face</name>
<pose>Unspecified</pose>
<truncated>1</truncated>
<difficult>0</difficult>
<bndbox>
<xmin>546</xmin>
<ymin>200</ymin>
<xmax>566</xmax>
<ymax>225</ymax>
</bndbox>
</object>
<object>
<name>face</name>
<pose>Unspecified</pose>
<truncated>1</truncated>
<difficult>0</difficult>
<bndbox>
<xmin>389</xmin>
<ymin>277</ymin>
<xmax>483</xmax>
<ymax>381</ymax>
</bndbox>
</object>
<object>
<name>face</name>
<pose>Unspecified</pose>
<truncated>1</truncated>
<difficult>0</difficult>
<bndbox>
<xmin>455</xmin>
<ymin>185</ymin>
<xmax>477</xmax>
<ymax>215</ymax>
</bndbox>
</object>
<object>
<name>face</name>
<pose>Unspecified</pose>
<truncated>1</truncated>
<difficult>0</difficult>
<bndbox>
<xmin>484</xmin>
<ymin>189</ymin>
<xmax>501</xmax>
<ymax>215</ymax>
</bndbox>
</object>
<object>
<name>face</name>
<pose>Unspecified</pose>
<truncated>1</truncated>
<difficult>0</difficult>
<bndbox>
<xmin>436</xmin>
<ymin>123</ymin>
<xmax>453</xmax>
<ymax>151</ymax>
</bndbox>
</object>
<object>
<name>face</name>
<pose>Unspecified</pose>
<truncated>1</truncated>
<difficult>0</difficult>
<bndbox>
<xmin>417</xmin>
<ymin>128</ymin>
<xmax>434</xmax>
<ymax>155</ymax>
</bndbox>
</object>
<object>
<name>face</name>
<pose>Unspecified</pose>
<truncated>1</truncated>
<difficult>0</difficult>
<bndbox>
<xmin>387</xmin>
<ymin>135</ymin>
<xmax>406</xmax>
<ymax>158</ymax>
</bndbox>
</object>
<object>
<name>face</name>
<pose>Unspecified</pose>
<truncated>1</truncated>
<difficult>0</difficult>
<bndbox>
<xmin>386</xmin>
<ymin>189</ymin>
<xmax>410</xmax>
<ymax>218</ymax>
</bndbox>
</object>
<object>
<name>face</name>
<pose>Unspecified</pose>
<truncated>1</truncated>
<difficult>0</difficult>
<bndbox>
<xmin>350</xmin>
<ymin>194</ymin>
<xmax>370</xmax>
<ymax>218</ymax>
</bndbox>
</object>
<object>
<name>face</name>
<pose>Unspecified</pose>
<truncated>1</truncated>
<difficult>0</difficult>
<bndbox>
<xmin>265</xmin>
<ymin>66</ymin>
<xmax>283</xmax>
<ymax>91</ymax>
</bndbox>
</object>
<object>
<name>face</name>
<pose>Unspecified</pose>
<truncated>1</truncated>
<difficult>0</difficult>
<bndbox>
<xmin>277</xmin>
<ymin>119</ymin>
<xmax>293</xmax>
<ymax>143</ymax>
</bndbox>
</object>
<object>
<name>face</name>
<pose>Unspecified</pose>
<truncated>1</truncated>
<difficult>0</difficult>
<bndbox>
<xmin>266</xmin>
<ymin>206</ymin>
<xmax>285</xmax>
<ymax>229</ymax>
</bndbox>
</object>
<object>
<name>face</name>
<pose>Unspecified</pose>
<truncated>1</truncated>
<difficult>0</difficult>
<bndbox>
<xmin>160</xmin>
<ymin>178</ymin>
<xmax>176</xmax>
<ymax>199</ymax>
</bndbox>
</object>
<object>
<name>face</name>
<pose>Unspecified</pose>
<truncated>1</truncated>
<difficult>0</difficult>
<bndbox>
<xmin>189</xmin>
<ymin>127</ymin>
<xmax>204</xmax>
<ymax>151</ymax>
</bndbox>
</object>
<object>
<name>face</name>
<pose>Unspecified</pose>
<truncated>1</truncated>
<difficult>0</difficult>
<bndbox>
<xmin>154</xmin>
<ymin>132</ymin>
<xmax>170</xmax>
<ymax>158</ymax>
</bndbox>
</object>
<object>
<name>face</name>
<pose>Unspecified</pose>
<truncated>1</truncated>
<difficult>0</difficult>
<bndbox>
<xmin>85</xmin>
<ymin>105</ymin>
<xmax>104</xmax>
<ymax>132</ymax>
</bndbox>
</object>
<object>
<name>face</name>
<pose>Unspecified</pose>
<truncated>1</truncated>
<difficult>0</difficult>
<bndbox>
<xmin>122</xmin>
<ymin>178</ymin>
<xmax>140</xmax>
<ymax>201</ymax>
</bndbox>
</object>
<object>
<name>face</name>
<pose>Unspecified</pose>
<truncated>1</truncated>
<difficult>0</difficult>
<bndbox>
<xmin>110</xmin>
<ymin>195</ymin>
<xmax>130</xmax>
<ymax>218</ymax>
</bndbox>
</object>
<object>
<name>face</name>
<pose>Unspecified</pose>
<truncated>1</truncated>
<difficult>0</difficult>
<bndbox>
<xmin>94</xmin>
<ymin>184</ymin>
<xmax>109</xmax>
<ymax>201</ymax>
</bndbox>
</object>
<object>
<name>face</name>
<pose>Unspecified</pose>
<truncated>1</truncated>
<difficult>0</difficult>
<bndbox>
<xmin>65</xmin>
<ymin>196</ymin>
<xmax>85</xmax>
<ymax>220</ymax>
</bndbox>
</object>
<object>
<name>face</name>
<pose>Unspecified</pose>
<truncated>1</truncated>
<difficult>0</difficult>
<bndbox>
<xmin>33</xmin>
<ymin>191</ymin>
<xmax>52</xmax>
<ymax>215</ymax>
</bndbox>
</object>
</annotation>
