<?xml version="1.0" ?>
<annotation>
<folder>widerface</folder>
<filename>58--Hockey_58_Hockey_icehockey_puck_58_235.jpg</filename>
<source>
<database>wider face Database</database>
<annotation>PASCAL VOC2007</annotation>
<image>flickr</image>
<flickrid>-1</flickrid>
</source>
<owner>
<flickrid>yanyu</flickrid>
<name>yanyu</name>
</owner>
<size>
<width>1024</width>
<height>768</height>
<depth>3</depth>
</size>
<segmented>0</segmented>
<object>
<name>face</name>
<pose>Unspecified</pose>
<truncated>1</truncated>
<difficult>0</difficult>
<bndbox>
<xmin>430</xmin>
<ymin>53</ymin>
<xmax>469</xmax>
<ymax>95</ymax>
</bndbox>
<lm>
<x1>451.634</x1>
<y1>62.701</y1>
<x2>465.067</x2>
<y2>63.491</y2>
<x3>459.536</x3>
<y3>75.08</y3>
<x4>448.473</x4>
<y4>79.558</y4>
<x5>460.853</x5>
<y5>79.558</y5>
<visible>1</visible>
<blur>0.57</blur>
</lm>
<has_lm>1</has_lm>
</object>
<object>
<name>face</name>
<pose>Unspecified</pose>
<truncated>1</truncated>
<difficult>0</difficult>
<bndbox>
<xmin>517</xmin>
<ymin>184</ymin>
<xmax>557</xmax>
<ymax>226</ymax>
</bndbox>
<lm>
<x1>544.804</x1>
<y1>196.964</y1>
<x2>552.304</x2>
<y2>198.036</y2>
<x3>555.786</x3>
<y3>211.161</y3>
<x4>534.089</x4>
<y4>216.25</y4>
<x5>538.911</x5>
<y5>217.054</y5>
<visible>1</visible>
<blur>0.44</blur>
</lm>
<has_lm>1</has_lm>
</object>
</annotation>
