<?xml version="1.0" ?>
<annotation>
<folder>widerface</folder>
<filename>7--Cheering_7_Cheering_Cheering_7_434.jpg</filename>
<source>
<database>wider face Database</database>
<annotation>PASCAL VOC2007</annotation>
<image>flickr</image>
<flickrid>-1</flickrid>
</source>
<owner>
<flickrid>yanyu</flickrid>
<name>yanyu</name>
</owner>
<size>
<width>1024</width>
<height>870</height>
<depth>3</depth>
</size>
<segmented>0</segmented>
<object>
<name>face</name>
<pose>Unspecified</pose>
<truncated>1</truncated>
<difficult>0</difficult>
<bndbox>
<xmin>104</xmin>
<ymin>228</ymin>
<xmax>137</xmax>
<ymax>284</ymax>
</bndbox>
<lm>
<x1>108.509</x1>
<y1>246.683</y1>
<x2>121.558</x2>
<y2>247.741</y2>
<x3>108.509</x3>
<y3>256.558</y3>
<x4>110.625</x4>
<y4>266.786</y4>
<x5>120.5</x5>
<y5>266.433</y5>
<visible>0</visible>
<blur>0.56</blur>
</lm>
<has_lm>1</has_lm>
</object>
<object>
<name>face</name>
<pose>Unspecified</pose>
<truncated>1</truncated>
<difficult>0</difficult>
<bndbox>
<xmin>213</xmin>
<ymin>210</ymin>
<xmax>249</xmax>
<ymax>244</ymax>
</bndbox>
<lm>
<x1>221.0</x1>
<y1>222.0</y1>
<x2>236.0</x2>
<y2>221.0</y2>
<x3>226.0</x3>
<y3>231.0</y3>
<x4>225.0</x4>
<y4>238.0</y4>
<x5>234.0</x5>
<y5>238.0</y5>
<visible>0</visible>
<blur>0.28</blur>
</lm>
<has_lm>1</has_lm>
</object>
<object>
<name>face</name>
<pose>Unspecified</pose>
<truncated>1</truncated>
<difficult>0</difficult>
<bndbox>
<xmin>300</xmin>
<ymin>259</ymin>
<xmax>346</xmax>
<ymax>321</ymax>
</bndbox>
<lm>
<x1>310.0</x1>
<y1>283.0</y1>
<x2>332.0</x2>
<y2>282.0</y2>
<x3>319.0</x3>
<y3>293.0</y3>
<x4>311.0</x4>
<y4>301.0</y4>
<x5>331.0</x5>
<y5>302.0</y5>
<visible>0</visible>
<blur>0.59</blur>
</lm>
<has_lm>1</has_lm>
</object>
<object>
<name>face</name>
<pose>Unspecified</pose>
<truncated>1</truncated>
<difficult>0</difficult>
<bndbox>
<xmin>464</xmin>
<ymin>245</ymin>
<xmax>509</xmax>
<ymax>310</ymax>
</bndbox>
<lm>
<x1>479.339</x1>
<y1>267.554</y1>
<x2>499.464</x2>
<y2>267.964</y2>
<x3>489.196</x3>
<y3>281.929</y3>
<x4>476.464</x4>
<y4>286.857</y4>
<x5>495.768</x5>
<y5>287.268</y5>
<visible>0</visible>
<blur>0.63</blur>
</lm>
<has_lm>1</has_lm>
</object>
<object>
<name>face</name>
<pose>Unspecified</pose>
<truncated>1</truncated>
<difficult>0</difficult>
<bndbox>
<xmin>249</xmin>
<ymin>230</ymin>
<xmax>276</xmax>
<ymax>280</ymax>
</bndbox>
<has_lm>0</has_lm>
</object>
<object>
<name>face</name>
<pose>Unspecified</pose>
<truncated>1</truncated>
<difficult>0</difficult>
<bndbox>
<xmin>710</xmin>
<ymin>268</ymin>
<xmax>743</xmax>
<ymax>319</ymax>
</bndbox>
<lm>
<x1>732.692</x1>
<y1>284.375</y1>
<x2>732.692</x2>
<y2>284.375</y2>
<x3>741.817</x3>
<y3>290.893</y3>
<x4>735.625</x4>
<y4>303.929</y4>
<x5>735.625</x5>
<y5>303.929</y5>
<visible>1</visible>
<blur>0.56</blur>
</lm>
<has_lm>1</has_lm>
</object>
<object>
<name>face</name>
<pose>Unspecified</pose>
<truncated>1</truncated>
<difficult>0</difficult>
<bndbox>
<xmin>738</xmin>
<ymin>222</ymin>
<xmax>763</xmax>
<ymax>260</ymax>
</bndbox>
<lm>
<x1>753.0</x1>
<y1>237.0</y1>
<x2>755.0</x2>
<y2>235.0</y2>
<x3>761.0</x3>
<y3>243.0</y3>
<x4>753.0</x4>
<y4>250.0</y4>
<x5>756.0</x5>
<y5>249.0</y5>
<visible>1</visible>
<blur>0.39</blur>
</lm>
<has_lm>1</has_lm>
</object>
<object>
<name>face</name>
<pose>Unspecified</pose>
<truncated>1</truncated>
<difficult>0</difficult>
<bndbox>
<xmin>867</xmin>
<ymin>162</ymin>
<xmax>878</xmax>
<ymax>179</ymax>
</bndbox>
<lm>
<x1>872.0</x1>
<y1>168.0</y1>
<x2>878.0</x2>
<y2>168.0</y2>
<x3>876.0</x3>
<y3>171.0</y3>
<x4>872.0</x4>
<y4>174.0</y4>
<x5>876.0</x5>
<y5>174.0</y5>
<visible>0</visible>
<blur>0.23</blur>
</lm>
<has_lm>1</has_lm>
</object>
<object>
<name>face</name>
<pose>Unspecified</pose>
<truncated>1</truncated>
<difficult>0</difficult>
<bndbox>
<xmin>910</xmin>
<ymin>231</ymin>
<xmax>940</xmax>
<ymax>265</ymax>
</bndbox>
<lm>
<x1>909.0</x1>
<y1>245.0</y1>
<x2>912.0</x2>
<y2>245.0</y2>
<x3>907.0</x3>
<y3>255.0</y3>
<x4>912.0</x4>
<y4>261.0</y4>
<x5>914.0</x5>
<y5>261.0</y5>
<visible>0</visible>
<blur>0.23</blur>
</lm>
<has_lm>1</has_lm>
</object>
</annotation>
